anaspro/__init__.py
anaspro/generator.py
anaspro/data/countries.json
anaspro-1.0.0.dist-info/LICENSE
anaspro-1.0.0.dist-info/METADATA
anaspro-1.0.0.dist-info/WHEEL
anaspro-1.0.0.dist-info/top_level.txt
anaspro-1.0.0.dist-info/RECORD
