Metadata-Version: 2.1
Name: anaspro
Version: 1.0.0
Summary: A library to generate random user data
Home-page: https://github.com/xxxxx/anaspro
Author: Anas Pro
Author-email: anaspro@example.com
Classifier: Programming Language :: Python :: 3
Classifier: License :: OSI Approved :: MIT License
Classifier: Operating System :: OS Independent
Requires-Python: >=3.6
License-File: LICENSE
Requires-Dist: Faker >=9.0.0
